split_layer/__init__.py
split_layer/split_layer.py
split_layer-0.1.1.dist-info/METADATA
split_layer-0.1.1.dist-info/RECORD
split_layer-0.1.1.dist-info/WHEEL
split_layer-0.1.1.dist-info/entry_points.txt
split_layer-0.1.1.dist-info/top_level.txt
