Metadata-Version: 2.1
Name: split-layer
Version: 0.1.1
Summary: Print each layer forward and backward time of PyTorch models.
Home-page: UNKNOWN
Author: swordfate
Author-email: 1317732065@qq.com
License: UNKNOWN
Platform: UNKNOWN
